DecisionTree-3.4.3.html
MANIFEST.in
Makefile
README
setup.cfg
setup.py
BoostedDecisionTree/BoostedDecisionTree.py
BoostedDecisionTree/__init__.py
DecisionTree/DecisionTree.py
DecisionTree/__init__.py
DecisionTree.egg-info/PKG-INFO
DecisionTree.egg-info/SOURCES.txt
DecisionTree.egg-info/dependency_links.txt
DecisionTree.egg-info/top_level.txt
DecisionTreeWithBagging/DecisionTreeWithBagging.py
DecisionTreeWithBagging/__init__.py
Examples/README
Examples/classify_by_asking_questions.py
Examples/classify_test_data_in_a_file.py
Examples/construct_dt_and_classify_one_sample_case1.py
Examples/construct_dt_and_classify_one_sample_case2.py
Examples/construct_dt_and_classify_one_sample_case3.py
Examples/construct_dt_and_classify_one_sample_case4.py
Examples/construct_dt_for_heavytailed.py
Examples/evaluate_training_data1.py
Examples/evaluate_training_data2.py
Examples/generate_training_data_numeric.py
Examples/generate_training_data_symbolic.py
Examples/get_indexes_associated_with_fields.py
Examples/heavytailed.csv
Examples/introspection_in_a_loop_interactive.py
Examples/introspection_show_training_samples_at_all_nodes_direct_influence.py
Examples/introspection_show_training_samples_to_nodes_influence_propagation.py
Examples/param_numeric.txt
Examples/param_numeric_extremely_overlapping_classes.txt
Examples/param_numeric_strongly_overlapping_classes.txt
Examples/param_symbolic.txt
Examples/stage3cancer.csv
Examples/test4.csv
Examples/test4_no_class_labels.csv
Examples/training.csv
Examples/training2.csv
Examples/training3.csv
Examples/training4.csv
Examples/training_symbolic.csv
ExamplesBagging/README_for_bagging_examples
ExamplesBagging/bagging_for_bulk_classification.py
ExamplesBagging/bagging_for_classifying_one_test_sample.py
ExamplesBagging/stage3cancer.csv
ExamplesBagging/test5.csv
ExamplesBagging/training5.csv
ExamplesBoosting/README_for_boosting_examples
ExamplesBoosting/boosting_for_bulk_classification.py
ExamplesBoosting/boosting_for_classifying_one_test_sample_1.py
ExamplesBoosting/boosting_for_classifying_one_test_sample_2.py
ExamplesBoosting/out6.csv
ExamplesBoosting/stage3cancer.csv
