Metadata-Version: 1.1
Name: DecisionTree
Version: 3.4.3
Summary: A Python module for decision-tree based classification of multidimensional data
Home-page: https://engineering.purdue.edu/kak/distDT/DecisionTree-3.4.3.html
Author: Avinash Kak
Author-email: kak@purdue.edu
License: Python Software Foundation License
Download-URL: https://engineering.purdue.edu/kak/distDT/DecisionTree-3.4.3.tar.gz#md5=cf0e589093499aeda9ec94f057685d6b
Keywords: data classification,decision trees,data analytics,regression
Platform: All platforms
Classifier: Topic :: Scientific/Engineering :: Information Analysis
Classifier: Programming Language :: Python :: 2.7
Classifier: Programming Language :: Python :: 3.4
